esperanto/__init__.py
esperanto/factory.py
esperanto/model_discovery.py
esperanto/py.typed
esperanto/common_types/CLAUDE.md
esperanto/common_types/__init__.py
esperanto/common_types/exceptions.py
esperanto/common_types/model.py
esperanto/common_types/reranker.py
esperanto/common_types/response.py
esperanto/common_types/stt.py
esperanto/common_types/task_type.py
esperanto/common_types/tts.py
esperanto/common_types/validation.py
esperanto/providers/CLAUDE.md
esperanto/providers/__init__.py
esperanto/providers/embedding/CLAUDE.md
esperanto/providers/embedding/__init__.py
esperanto/providers/embedding/azure.py
esperanto/providers/embedding/base.py
esperanto/providers/embedding/google.py
esperanto/providers/embedding/jina.py
esperanto/providers/embedding/mistral.py
esperanto/providers/embedding/ollama.py
esperanto/providers/embedding/openai.py
esperanto/providers/embedding/openai_compatible.py
esperanto/providers/embedding/openrouter.py
esperanto/providers/embedding/transformers.py
esperanto/providers/embedding/vertex.py
esperanto/providers/embedding/voyage.py
esperanto/providers/llm/CLAUDE.md
esperanto/providers/llm/__init__.py
esperanto/providers/llm/anthropic.py
esperanto/providers/llm/azure.py
esperanto/providers/llm/base.py
esperanto/providers/llm/deepseek.py
esperanto/providers/llm/google.py
esperanto/providers/llm/groq.py
esperanto/providers/llm/mistral.py
esperanto/providers/llm/ollama.py
esperanto/providers/llm/openai.py
esperanto/providers/llm/openai_compatible.py
esperanto/providers/llm/openrouter.py
esperanto/providers/llm/perplexity.py
esperanto/providers/llm/vertex.py
esperanto/providers/llm/xai.py
esperanto/providers/reranker/CLAUDE.md
esperanto/providers/reranker/__init__.py
esperanto/providers/reranker/base.py
esperanto/providers/reranker/jina.py
esperanto/providers/reranker/transformers.py
esperanto/providers/reranker/voyage.py
esperanto/providers/stt/CLAUDE.md
esperanto/providers/stt/__init__.py
esperanto/providers/stt/azure.py
esperanto-2.18.0.dist-info/METADATA
esperanto-2.18.0.dist-info/WHEEL
esperanto-2.18.0.dist-info/licenses/LICENSE
esperanto-2.18.0.dist-info/RECORD
