Metadata-Version: 2.4
Name: esperanto
Version: 2.18.0
Summary: A light-weight, production-ready, unified interface for various AI model providers
Project-URL: repository, https://github.com/lfnovo/esperanto
Project-URL: homepage, https://github.com/lfnovo/esperanto
Project-URL: documentation, https://github.com/lfnovo/esperanto#readme
Author-email: LUIS NOVO <lfnovo@gmail.com>
License: MIT
License-File: LICENSE
Keywords: ai,anthropic,deepseek,elevenlabs,gemini,google,groq,llm,mistral,openai,openrouter,speech-to-text,text-to-speech,transformers,x.ai
Requires-Python: <3.14,>=3.10
Requires-Dist: httpx>=0.28.0
Requires-Dist: pydantic>=2.0.0
Provides-Extra: transformers
Requires-Dist: accelerate<2.0.0,>=1.12.0; extra == 'transformers'
Requires-Dist: einops>=0.8.1; extra == 'transformers'
Requires-Dist: numpy<3.0.0,>=2.2.6; extra == 'transformers'
Requires-Dist: scikit-learn<2.0.0,>=1.7.2; extra == 'transformers'
Requires-Dist: sentence-transformers<6.0.0,>=5.2.0; extra == 'transformers'
Requires-Dist: tokenizers<1.0.0,>=0.22.1; extra == 'transformers'
Requires-Dist: torch<3.0.0,>=2.9.1; extra == 'transformers'
Requires-Dist: transformers<5.0.0,>=4.57.3; extra == 'transformers'
Provides-Extra: validation
Requires-Dist: jsonschema<5.0.0,>=4.0.0; extra == 'validation'
